excel_framework/__init__.py
excel_framework/buildables/__init__.py
excel_framework/buildables/layout/column.py
excel_framework/buildables/layout/row.py
excel_framework/buildables/layout/table.py
excel_framework/buildables/non_layout/excel_cell.py
excel_framework/excel/__init__.py
excel_framework/excel/excel_file.py
excel_framework/excel/excel_sheet.py
excel_framework/internals/__init__.py
excel_framework/internals/build_context.py
excel_framework/internals/buildable.py
excel_framework/sizes/__init__.py
excel_framework/sizes/dimension.py
excel_framework/sizes/resizer.py
excel_framework/sizes/size.py
excel_framework/styling/__init__.py
excel_framework/styling/border.py
excel_framework/styling/color.py
excel_framework/styling/fill.py
excel_framework/styling/style.py
excel_framework/styling/style_part.py
excel_framework/styling/styler.py
excel_framework/styling/text_style.py
excel_framework-0.4.5.dist-info/METADATA
excel_framework-0.4.5.dist-info/WHEEL
excel_framework-0.4.5.dist-info/licenses/LICENSE
excel_framework-0.4.5.dist-info/RECORD
