Metadata-Version: 2.1
Name: excel_framework
Version: 0.4.5
Summary: A framework for creating excel files declaratively.
Project-URL: Homepage, https://github.com/TheUltimateOptimist/excel_framework
Project-URL: Bug Tracker, https://github.com/TheUltimateOptimist/excel_framework/issues
Author-email: Jonathan Dück <jonathan.dueck@digital-confidence.de>
License-File: LICENSE
Classifier: License :: OSI Approved :: MIT License
Classifier: Operating System :: OS Independent
Classifier: Programming Language :: Python :: 3
Requires-Python: >=3.7
Requires-Dist: openpyxl
Requires-Dist: overrides
